.gitignore
.travis.yml
LICENSE
MANIFEST.in
README.rst
setup.cfg
setup.py
tox.ini
cloudbench/__init__.py
cloudbench/cli.py
cloudbench/version.py
cloudbench.egg-info/PKG-INFO
cloudbench.egg-info/SOURCES.txt
cloudbench.egg-info/dependency_links.txt
cloudbench.egg-info/entry_points.txt
cloudbench.egg-info/requires.txt
cloudbench.egg-info/top_level.txt
cloudbench/api/__init__.py
cloudbench/api/auth.py
cloudbench/api/client.py
cloudbench/api/exceptions.py
cloudbench/api/factory.py
cloudbench/api/util.py
cloudbench/cloud/__init__.py
cloudbench/cloud/base.py
cloudbench/cloud/ec2.py
cloudbench/cloud/exceptions.py
cloudbench/cloud/gce.py
cloudbench/cloud/rackspace.py
cloudbench/cloud/utils.py
cloudbench/fio/__init__.py
cloudbench/fio/engine.py
cloudbench/fio/exceptions.py
cloudbench/fio/output.py
cloudbench/fio/config/__init__.py
cloudbench/fio/config/config.py
cloudbench/fio/config/job.py
cloudbench/fio/config/library.py
cloudbench/fio/report/__init__.py
cloudbench/fio/report/single.py
cloudbench/test/__init__.py
cloudbench/test/utils.py
cloudbench/test/api/__init__.py
cloudbench/test/api/test_auth.py
cloudbench/test/api/test_create.py
cloudbench/test/api/test_errors.py
cloudbench/test/api/test_get.py
cloudbench/test/api/test_list.py
cloudbench/test/api/test_update.py
cloudbench/test/cli/__init__.py
cloudbench/test/cli/test_api.py
cloudbench/test/cli/test_utils.py
cloudbench/test/cli/utils.py
cloudbench/test/cloud/__init__.py
cloudbench/test/cloud/rackspace_utils.py
cloudbench/test/cloud/test_ec2.py
cloudbench/test/cloud/test_gce.py
cloudbench/test/cloud/test_identify.py
cloudbench/test/cloud/test_rackspace.py
cloudbench/test/cloud/test_utils.py
cloudbench/test/fio/__init__.py
cloudbench/test/fio/test_config.py
cloudbench/test/fio/test_engine.py
cloudbench/test/fio/test_output.py
cloudbench/test/fio/test_report.py
cloudbench/utils/__init__.py
cloudbench/utils/daemon.py
cloudbench/utils/freeze.py
cloudbench/utils/fs.py
cloudbench/utils/math.py
scalr/scripts/cloudbench.configure.sh
scalr/scripts/cloudbench.execute.sh
scalr/scripts/cloudbench.install.sh